iode/__init__.py
iode/__init__.pyi
iode/cli.py
iode/cli.pyi
iode/common.py
iode/common.pyi
iode/compute/__init__.py
iode/compute/__init__.pyi
iode/compute/estimation.py
iode/compute/estimation.pyi
iode/compute/simulation.py
iode/compute/simulation.pyi
iode/computed_table/__init__.py
iode/computed_table/__init__.pyi
iode/computed_table/computed_table.py
iode/computed_table/computed_table.pyi
iode/deprecated/__init__.py
iode/deprecated/__init__.pyi
iode/deprecated/compat_larray.py
iode/deprecated/compat_larray.pyi
iode/deprecated/compat_pandas.py
iode/deprecated/compat_pandas.pyi
iode/deprecated/estimation.py
iode/deprecated/estimation.pyi
iode/deprecated/iode_objects.py
iode/deprecated/iode_objects.pyi
iode/deprecated/lec.py
iode/deprecated/lec.pyi
iode/deprecated/model.py
iode/deprecated/model.pyi
iode/deprecated/report.py
iode/deprecated/report.pyi
iode/deprecated/time.py
iode/deprecated/time.pyi
iode/deprecated/workspace.py
iode/deprecated/workspace.pyi
iode/doc/iode.chm
iode/doc/iode.pdf
iode/gui.py
iode/gui.pyi
iode/iode_cython.cp310-win_amd64.pyd
iode/iode_cython.pyi
iode/iode_database/abstract_database.py
iode/iode_database/comments_database.py
iode/iode_database/equations_database.py
iode/iode_database/extra_files.py
iode/iode_database/identities_database.py
iode/iode_database/lists_database.py
iode/iode_database/scalars_database.py
iode/iode_database/tables_database.py
iode/iode_database/variables_database.py
iode/lec.py
iode/lec.pyi
iode/objects/__init__.py
iode/objects/__init__.pyi
iode/objects/equation.py
iode/objects/equation.pyi
iode/objects/identity.py
iode/objects/identity.pyi
iode/objects/scalar.py
iode/objects/scalar.pyi
iode/objects/table.py
iode/objects/table.pyi
iode/reports.py
iode/reports.pyi
iode/super.py
iode/super.pyi
iode/tests/data/a.var
iode/tests/data/fun.ac
iode/tests/data/fun.ae
iode/tests/data/fun.ai
iode/tests/data/fun.al
iode/tests/data/fun.as
iode/tests/data/fun.at
iode/tests/data/fun.av
iode/tests/data/fun.cmt
iode-7.0.4.dist-info/METADATA
iode-7.0.4.dist-info/WHEEL
iode-7.0.4.dist-info/entry_points.txt
iode-7.0.4.dist-info/licenses/LICENSE.md
iode-7.0.4.dist-info/RECORD
