Metadata-Version: 2.1
Name: iode
Version: 7.0.4
Summary: IODE is a package dedicated to econometric models and to the management of statistical series
Author-Email: Alix Damman <ald@plan.be>, Yannick Van den Abbeel <yvda@plan.be>, Jean-Marc Paul <jmarc.paul@gmail.com>, Geert Bryon <gb@plan.be>
Classifier: Development Status :: 4 - Beta
Classifier: License :: OSI Approved :: GNU General Public License v3 (GPLv3)
Classifier: Operating System :: Microsoft :: Windows
Classifier: Intended Audience :: Science/Research
Classifier: Intended Audience :: Developers
Classifier: Programming Language :: Python
Classifier: Programming Language :: Python :: 3
Classifier: Programming Language :: Python :: 3.10
Classifier: Programming Language :: Python :: 3.11
Classifier: Programming Language :: Python :: 3.12
Classifier: Topic :: Scientific/Engineering
Classifier: Topic :: Software Development :: Libraries
Project-URL: Homepage, https://iode.readthedocs.io/en/stable/
Requires-Python: >=3.10
Requires-Dist: numpy
Requires-Dist: pandas
Requires-Dist: matplotlib
